error_parameters_calculator.py
error_param_cal-0.0.6.dist-info/LICENSE
error_param_cal-0.0.6.dist-info/METADATA
error_param_cal-0.0.6.dist-info/WHEEL
error_param_cal-0.0.6.dist-info/top_level.txt
error_param_cal-0.0.6.dist-info/RECORD
