Metadata-Version: 2.1
Name: error-param-cal
Version: 0.0.6
Summary: UNKNOWN
Home-page: https://github.com/SuhasVS95/Hypothesis_Testing_Error_parameters_Calculator
Author: Suhas V S
Author-email: <suhas95vs@gmail.com>
License: MIT
Keywords: python,sample_size,Type I Error,Type II Error,False Positive,False Negative,Power of Test
Platform: UNKNOWN
Classifier: Development Status :: 1 - Planning
Classifier: Intended Audience :: Developers
Classifier: Programming Language :: Python :: 3
Classifier: Operating System :: Unix
Classifier: Operating System :: MacOS :: MacOS X
Classifier: Operating System :: Microsoft :: Windows
